setup.cfg
setup.py
griboedov/__init__.py
griboedov/проверка_элементов.py
griboedov/работа_с_файлами.py
griboedov/терминал.py
griboedov.egg-info/PKG-INFO
griboedov.egg-info/SOURCES.txt
griboedov.egg-info/dependency_links.txt
griboedov.egg-info/not-zip-safe
griboedov.egg-info/top_level.txt