Metadata-Version: 2.1
Name: griboedov
Version: 0.1
Summary: ...
Author-email: panufriev258@gmail.com
